janus/__init__.py
janus/crossover.py
janus/features.py
janus/fragment.py
janus/janus.py
janus/mutate.py
janus/network.py
janus/utils.py
janus_ga-1.0.3.dist-info/LICENSE
janus_ga-1.0.3.dist-info/METADATA
janus_ga-1.0.3.dist-info/WHEEL
janus_ga-1.0.3.dist-info/top_level.txt
janus_ga-1.0.3.dist-info/RECORD
