Metadata-Version: 2.1
Name: janus-ga
Version: 1.0.3
Summary: JANUS: Parallel Tempered Genetic Algorithm Guided by Deep Neural Networks for Inverse Molecular Design
Home-page: https://github.com/aspuru-guzik-group/janus
Author: Gary Tom, AkshatKumar Nigam, Robert Pollice, Alán Aspuru-Guzik
Author-email: akshat.nigam@mail.utoronto.ca
License: Apache License 2.0
Keywords: Genetic Algorithm,Inverse Molecular Design,Deep Neural Networks
Classifier: Programming Language :: Python :: 3
Classifier: Programming Language :: Python :: 3.7
Classifier: Operating System :: POSIX :: Linux
Requires-Python: >=3.7
License-File: LICENSE
Requires-Dist: torch (>=1.9.0)
Requires-Dist: selfies (==1.0.3)
Requires-Dist: numpy (>=1.17.0)
Requires-Dist: pyyaml (>=6.0)
